mygalaxy/__init__.py
mygalaxy/calc.py
mygalaxy/planet.py
mygalaxy-0.1.2.dist-info/WHEEL
mygalaxy-0.1.2.dist-info/METADATA
mygalaxy-0.1.2.dist-info/RECORD
